Netaxgenespo/__init__.py
Netaxgenespo/network.cpython-311-darwin.so
Netaxgenespo-0.1.1.dist-info/LICENSE.txt
Netaxgenespo-0.1.1.dist-info/METADATA
Netaxgenespo-0.1.1.dist-info/WHEEL
Netaxgenespo-0.1.1.dist-info/top_level.txt
Netaxgenespo-0.1.1.dist-info/RECORD
